tracker.py
redis_tracker-1.1.dist-info/entry_points.txt
redis_tracker-1.1.dist-info/WHEEL
redis_tracker-1.1.dist-info/METADATA
redis_tracker-1.1.dist-info/RECORD
