Metadata-Version: 2.1
Name: redis-tracker
Version: 1.1
Summary: simple redis key tracker for stdout and prometheus
License: GPL-3.0-or-later
Author: bernardas ališauskas
Author-email: bernardas.alisauskas@pm.me
Requires-Python: >=3.6,<4.0
Classifier: Environment :: Console
Classifier: Intended Audience :: Developers
Classifier: License :: OSI Approved :: GNU General Public License v3 or later (GPLv3+)
Classifier: Operating System :: POSIX
Classifier: Programming Language :: Python :: 3
Classifier: Programming Language :: Python :: 3.6
Classifier: Programming Language :: Python :: 3.7
Classifier: Programming Language :: Python :: 3.8
Requires-Dist: click (>=7.1.2,<8.0.0)
Requires-Dist: redis (>=3.5.3,<4.0.0)
